pyhon/__init__.py
pyhon/__main__.py
pyhon/appliance.py
pyhon/attributes.py
pyhon/command_loader.py
pyhon/commands.py
pyhon/const.py
pyhon/diagnose.py
pyhon/exceptions.py
pyhon/helper.py
pyhon/hon.py
pyhon/printer.py
pyhon/py.typed
pyhon/rules.py
pyhon/typedefs.py
pyhon/appliances/__init__.py
pyhon/appliances/base.py
pyhon/appliances/dw.py
pyhon/appliances/ov.py
pyhon/appliances/ref.py
pyhon/appliances/td.py
pyhon/appliances/wc.py
pyhon/appliances/wd.py
pyhon/appliances/wh.py
pyhon/appliances/wm.py
pyhon/connection/__init__.py
pyhon/connection/api.py
pyhon/connection/auth.py
pyhon/connection/device.py
pyhon/connection/mqtt.py
pyhon/connection/handler/__init__.py
pyhon/connection/handler/anonym.py
pyhon/connection/handler/auth.py
pyhon/connection/handler/base.py
pyhon/connection/handler/hon.py
pyhon/parameter/__init__.py
pyhon/parameter/base.py
pyhon/parameter/enum.py
pyhon/parameter/fixed.py
pyhon/parameter/program.py
pyhon/parameter/range.py
pyhon_2-0.17.5.dist-info/licenses/LICENSE
pyhon_2-0.17.5.dist-info/METADATA
pyhon_2-0.17.5.dist-info/WHEEL
pyhon_2-0.17.5.dist-info/entry_points.txt
pyhon_2-0.17.5.dist-info/top_level.txt
pyhon_2-0.17.5.dist-info/RECORD
