Metadata-Version: 2.4
Name: pyhOn-2
Version: 0.17.5
Summary: Control hOn devices with python
Author: Andre Basche
License: MIT
Project-URL: GitHub, https://github.com/Andre0512/pyhOn
Project-URL: PyPI, https://pypi.org/project/pyhOn
Platform: any
Classifier: Development Status :: 4 - Beta
Classifier: Environment :: Console
Classifier: License :: OSI Approved :: MIT License
Classifier: Natural Language :: English
Classifier: Operating System :: OS Independent
Classifier: Programming Language :: Python :: 3.10
Classifier: Programming Language :: Python :: 3.11
Classifier: Programming Language :: Python :: 3.12
Classifier: Topic :: Software Development :: Libraries :: Python Modules
Requires-Python: >=3.10
License-File: LICENSE
Requires-Dist: aiohttp>=3.8.6
Requires-Dist: typing-extensions>=4.8
Requires-Dist: yarl>=1.8
Requires-Dist: awsiotsdk>=1.21.0
Dynamic: author
Dynamic: classifier
Dynamic: description
Dynamic: description-content-type
Dynamic: license
Dynamic: license-file
Dynamic: platform
Dynamic: project-url
Dynamic: requires-dist
Dynamic: requires-python
Dynamic: summary
